compas_rv3/__init__.py
compas_rv3/__main__.py
compas_rv3/artists/__init__.py
compas_rv3/artists/diagramartist.py
compas_rv3/artists/forceartist.py
compas_rv3/artists/formartist.py
compas_rv3/artists/thrustartist.py
compas_rv3/blender/__init__.py
compas_rv3/datastructures/__init__.py
compas_rv3/datastructures/diagram.py
compas_rv3/datastructures/forcediagram.py
compas_rv3/datastructures/formdiagram.py
compas_rv3/datastructures/pattern.py
compas_rv3/datastructures/subdmesh.py
compas_rv3/datastructures/thrustdiagram.py
compas_rv3/ghpython/__init__.py
compas_rv3/objects/__init__.py
compas_rv3/objects/diagramobject.py
compas_rv3/objects/forceobject.py
compas_rv3/objects/formobject.py
compas_rv3/objects/patternobject.py
compas_rv3/objects/thrustobject.py
compas_rv3/rhino/__init__.py
compas_rv3/rhino/install.py
compas_rv3/rhino/register.py
compas_rv3/rhino/artists/__init__.py
compas_rv3/rhino/artists/diagramartist.py
compas_rv3/rhino/artists/forceartist.py
compas_rv3/rhino/artists/formartist.py
compas_rv3/rhino/artists/thrustartist.py
compas_rv3/rhino/conduits/__init__.py
compas_rv3/rhino/conduits/horizontalconduit.py
compas_rv3/rhino/conduits/subdconduit.py
compas_rv3/rhino/conduits/thrustconduit.py
compas_rv3/rhino/objects/__init__.py
compas_rv3/rhino/objects/diagramobject.py
compas_rv3/rhino/objects/forceobject.py
compas_rv3/rhino/objects/formobject.py
compas_rv3/rhino/objects/patternobject.py
compas_rv3/rhino/objects/thrustobject.py
compas_rv3/rhino/ui/RV3/dev/NOTES
compas_rv3/rhino/ui/RV3/dev/RV3__toolbar_cmd.py
compas_rv3/rhino/ui/RV3/dev/RV3_boundary_boundaries_cmd.py
compas_rv3/rhino/ui/RV3/dev/RV3_boundary_openings_cmd.py
compas_rv3/rhino/ui/RV3/dev/RV3_boundary_supports_cmd.py
compas_rv3/rhino/ui/RV3/dev/RV3_force_cmd.py
compas_rv3/rhino/ui/RV3/dev/RV3_force_modify_edges_cmd.py
compas_rv3/rhino/ui/RV3/dev/RV3_force_modify_vertices_cmd.py
compas_rv3/rhino/ui/RV3/dev/RV3_force_move_vertices_cmd.py
compas_rv3/rhino/ui/RV3/dev/RV3_form_cmd.py
compas_rv3-0.4.0.dist-info/AUTHORS.md
compas_rv3-0.4.0.dist-info/LICENSE
compas_rv3-0.4.0.dist-info/METADATA
compas_rv3-0.4.0.dist-info/WHEEL
compas_rv3-0.4.0.dist-info/top_level.txt
compas_rv3-0.4.0.dist-info/RECORD
