Metadata-Version: 2.1
Name: compas-rv3
Version: 0.4.0
Summary: Funicular form finding based on compas_tna
Home-page: https://github.com/BlockResearchGroup/compas_rv3
Author: Tom Van Mele, Juney Lee, Li Chen
Author-email: van.mele@arch.ethz.ch, juney-lee@som.com, li.chen@arch.ethz.ch
License: MIT license
Classifier: Development Status :: 4 - Beta
Classifier: Intended Audience :: Developers
Classifier: Topic :: Scientific/Engineering
Classifier: License :: OSI Approved :: MIT License
Classifier: Operating System :: Unix
Classifier: Operating System :: POSIX
Classifier: Operating System :: Microsoft :: Windows
Classifier: Programming Language :: Python
Classifier: Programming Language :: Python :: 3
Classifier: Programming Language :: Python :: 3.8
Classifier: Programming Language :: Python :: 3.9
Classifier: Programming Language :: Python :: 3.10
Classifier: Programming Language :: Python :: Implementation :: CPython
Requires-Python: >=3.8
License-File: LICENSE
License-File: AUTHORS.md
Requires-Dist: compas (>=1.17.3)
Requires-Dist: compas-cloud
Requires-Dist: compas-tna (>=0.2.0)
Requires-Dist: compas-ui (>=0.9.1)
